faucetbot/__init__.py
faucetbot/faucet.py
faucetbot/logger.py
faucetbot-0.1.0.dist-info/METADATA
faucetbot-0.1.0.dist-info/WHEEL
faucetbot-0.1.0.dist-info/entry_points.txt
faucetbot-0.1.0.dist-info/RECORD
