Metadata-Version: 2.4
Name: faucetbot
Version: 0.1.0
Summary: A bot to request USDC or EURC tokens every hour.
Author-email: Meek Msaki <meek10x+faucetbot@gmail.com>
Requires-Python: >=3.10
Requires-Dist: requests>=2.32.4
